browsercontrol/__init__.py
browsercontrol/__main__.py
browsercontrol/browser.py
browsercontrol/config.py
browsercontrol/server.py
browsercontrol/tools/__init__.py
browsercontrol/tools/content.py
browsercontrol/tools/devtools.py
browsercontrol/tools/forms.py
browsercontrol/tools/interaction.py
browsercontrol/tools/navigation.py
browsercontrol/tools/recording.py
browsercontrol-0.1.1.dist-info/METADATA
browsercontrol-0.1.1.dist-info/WHEEL
browsercontrol-0.1.1.dist-info/entry_points.txt
browsercontrol-0.1.1.dist-info/licenses/LICENSE
browsercontrol-0.1.1.dist-info/RECORD
