Metadata-Version: 2.4
Name: browsercontrol
Version: 0.1.1
Summary: MCP server for browser automation with Set of Marks (SoM) - AI agents can see and interact with web pages using numbered element IDs
Project-URL: Homepage, https://github.com/adityasasidhar/browsercontrol
Project-URL: Repository, https://github.com/adityasasidhar/browsercontrol
Author: Aditya Sasidhar
License: MIT
License-File: LICENSE
Keywords: agent,ai,automation,browser,llm,mcp,playwright
Classifier: Development Status :: 4 - Beta
Classifier: Intended Audience :: Developers
Classifier: License :: OSI Approved :: MIT License
Classifier: Programming Language :: Python :: 3
Classifier: Programming Language :: Python :: 3.11
Classifier: Programming Language :: Python :: 3.12
Classifier: Programming Language :: Python :: 3.13
Classifier: Topic :: Internet :: WWW/HTTP :: Browsers
Classifier: Topic :: Software Development :: Libraries :: Python Modules
Requires-Python: >=3.11
Requires-Dist: fastmcp>=2.14.2
Requires-Dist: markdownify>=0.14.1
Requires-Dist: pillow>=11.0.0
Requires-Dist: playwright>=1.49.0
